flask_filealchemy/__init__.py
flask_filealchemy/common.py
flask_filealchemy/filealchemy.py
flask_filealchemy/loaders.py
flask_filealchemy-0.9.0.dist-info/METADATA
flask_filealchemy-0.9.0.dist-info/WHEEL
flask_filealchemy-0.9.0.dist-info/licenses/LICENSE.txt
flask_filealchemy-0.9.0.dist-info/RECORD
