Metadata-Version: 2.4
Name: flask-filealchemy
Version: 0.9.0
Summary: YAML-formatted plain-text file based models for Flask backed by Flask-SQLAlchemy
Project-URL: Repository, https://github.com/siddhantgoel/flask-filealchemy
Project-URL: Documentation, https://github.com/siddhantgoel/flask-filealchemy
Author-email: Siddhant Goel <me@sgoel.dev>
License-Expression: MIT
License-File: LICENSE.txt
Keywords: flask,plaintext,sqlalchemy,web,yaml
Classifier: Development Status :: 4 - Beta
Classifier: Environment :: Web Environment
Classifier: Framework :: Flask
Classifier: License :: OSI Approved :: MIT License
Classifier: Programming Language :: Python :: 3
Classifier: Programming Language :: Python :: 3 :: Only
Classifier: Programming Language :: Python :: 3.9
Classifier: Programming Language :: Python :: 3.10
Classifier: Programming Language :: Python :: 3.11
Classifier: Programming Language :: Python :: 3.12
Classifier: Programming Language :: Python :: 3.13
Classifier: Topic :: Database
Classifier: Topic :: Database :: Front-Ends
Classifier: Topic :: Text Processing :: Markup
Requires-Python: >=3.9
Requires-Dist: flask-sqlalchemy>=3.1.1
Requires-Dist: flask>=3.1.0
Requires-Dist: python-frontmatter>=1.1.0
Requires-Dist: ruamel-yaml>=0.18.10
